sarp_codecs/__init__.py
sarp_codecs/codec.py
sarp_codecs/command_codec.py
sarp_codecs/fill_telem_codec.py
sarp_codecs/template_codec.py
sarp_codecs-1.1.8.dist-info/LICENSE
sarp_codecs-1.1.8.dist-info/METADATA
sarp_codecs-1.1.8.dist-info/WHEEL
sarp_codecs-1.1.8.dist-info/top_level.txt
sarp_codecs-1.1.8.dist-info/RECORD
