Metadata-Version: 2.1
Name: sarp-codecs
Version: 1.1.8
Summary: A package to encode network communication for SARP
Home-page: https://gitlab.com/SARP_UW/codecs
Author: Josh Sherbrooke
Author-email: jsherbro@gmail.com
License: UNKNOWN
Platform: UNKNOWN
Classifier: Programming Language :: Python :: 3
Classifier: License :: OSI Approved :: MIT License
Classifier: Operating System :: OS Independent
Requires-Python: >=3.6
